{
  "addresses": {
    "0xc2a30212a8ddac9e123944d6e29faddce994e5f2": {
      "positions": {},
      "lastNotifiedPositions": {}
    },
    "0xb317d2bc2d3d2df5fa441b5bae0ab9d8b07283ae": {
      "positions": {
        "BTC": {
          "szi": 572.71125,
          "positionValue": 45192644.7375,
          "entryPx": 91506.7,
          "unrealizedPnl": -7214310.342072,
          "liquidationPx": 37702.4375735962,
          "leverage": 5,
          "leverageType": "cross"
        },
        "ETH": {
          "szi": 188086.5175,
          "positionValue": 453796340.77225,
          "entryPx": 3149.42,
          "unrealizedPnl": -138568946.204738,
          "liquidationPx": 2284.5214556674,
          "leverage": 5,
          "leverageType": "cross"
        },
        "SOL": {
          "szi": 511612.85,
          "positionValue": 53115646.087,
          "entryPx": 130.1911,
          "unrealizedPnl": -13491810.7129,
          "liquidationPx": 57.0999085624,
          "leverage": 10,
          "leverageType": "cross"
        }
      },
      "lastNotifiedPositions": {
        "BTC": {
          "szi": 572.71125,
          "positionValue": 46588914.765,
          "entryPx": 91506.7,
          "unrealizedPnl": -5818040.314572,
          "liquidationPx": null,
          "leverage": 5,
          "leverageType": "cross"
        },
        "ETH": {
          "szi": 188086.5175,
          "positionValue": 474937265.33925,
          "entryPx": 3149.42,
          "unrealizedPnl": -117428021.637738,
          "liquidationPx": 2260.5253479021,
          "leverage": 5,
          "leverageType": "cross"
        },
        "SOL": {
          "szi": 511612.85,
          "positionValue": 56200671.5725,
          "entryPx": 130.1911,
          "unrealizedPnl": -10406785.2274,
          "liquidationPx": 13.4145785927,
          "leverage": 10,
          "leverageType": "cross"
        }
      }
    }
  }
}