{
  "addresses": {
    "0xc2a30212a8ddac9e123944d6e29faddce994e5f2": {
      "positions": {},
      "lastNotifiedPositions": {}
    },
    "0xb317d2bc2d3d2df5fa441b5bae0ab9d8b07283ae": {
      "positions": {
        "ETH": {
          "szi": 140094.5238,
          "positionValue": 447980258.75526,
          "entryPx": 3179.54,
          "unrealizedPnl": 2543095.71141,
          "liquidationPx": 2387.3192655074,
          "leverage": 5,
          "leverageType": "cross"
        }
      },
      "lastNotifiedPositions": {
        "ETH": {
          "szi": 140094.5238,
          "positionValue": 443749404.1365,
          "entryPx": 3179.54,
          "unrealizedPnl": -1687758.90735,
          "liquidationPx": 2387.2372554135,
          "leverage": 5,
          "leverageType": "cross"
        }
      }
    }
  }
}