{
  "addresses": {
    "0xc2a30212a8ddac9e123944d6e29faddce994e5f2": {
      "positions": {
        "BTC": {
          "szi": 223.32307,
          "positionValue": 23050737.31619,
          "entryPx": 102700,
          "unrealizedPnl": 115458.02719,
          "liquidationPx": 101400.1133923563,
          "leverage": 40,
          "leverageType": "cross"
        }
      },
      "lastNotifiedPositions": {
        "BTC": {
          "szi": 223.32307,
          "positionValue": 23027288.39384,
          "entryPx": 102700,
          "unrealizedPnl": 92009.10484,
          "liquidationPx": 101398.8080126136,
          "leverage": 40,
          "leverageType": "cross"
        }
      }
    },
    "0xb317d2bc2d3d2df5fa441b5bae0ab9d8b07283ae": {
      "positions": {
        "BTC": {
          "szi": 700,
          "positionValue": 72251900,
          "entryPx": 104520.3,
          "unrealizedPnl": -912312.04469,
          "liquidationPx": 50235.2535550061,
          "leverage": 5,
          "leverageType": "cross"
        },
        "ETH": {
          "szi": 16000,
          "positionValue": 54459200,
          "entryPx": 3427.14,
          "unrealizedPnl": -375149.38847,
          "liquidationPx": 1068.0091689986,
          "leverage": 5,
          "leverageType": "cross"
        }
      },
      "lastNotifiedPositions": {
        "BTC": {
          "szi": 600,
          "positionValue": 60934200,
          "entryPx": 104785.9,
          "unrealizedPnl": -1937372.71761,
          "liquidationPx": 43111.118862984,
          "leverage": 5,
          "leverageType": "cross"
        },
        "ETH": {
          "szi": 13000,
          "positionValue": 43019600,
          "entryPx": 3444.81,
          "unrealizedPnl": -1762944.48349,
          "liquidationPx": 591.053644138,
          "leverage": 5,
          "leverageType": "cross"
        }
      }
    }
  }
}